pyarts.libs/libz-d8a329de.so.1.2.7
pyarts.libs/libgfortran-4fc760a1.so.3.0.0
pyarts.libs/libgfortran-040039e1.so.5.0.0
pyarts.libs/libquadmath-30d679e1.so.0.0.0
pyarts.libs/libgomp-7c85b1e2.so.1.0.0
pyarts.libs/libtatlas-6cc7999c.so.3.10
pyarts/environment.py
pyarts/internals.py
pyarts/covariancematrix.py
pyarts/common.py
pyarts/__init__.py
pyarts/sensor.py
pyarts/spectroscopy.py
pyarts/types.py
pyarts/retrieval.py
pyarts/parser.py
pyarts/scattering.py
pyarts/catalogues.py
pyarts/griddedfield.py
pyarts/xsec.py
pyarts/constants.py
pyarts/controlfiles/general/general.arts
pyarts/controlfiles/general/planet_mars.arts
pyarts/controlfiles/general/continua.arts
pyarts/controlfiles/general/agendasDOIT.arts
pyarts/controlfiles/general/agendas_surface_sub.arts
pyarts/controlfiles/general/agendas_surface.arts
pyarts/controlfiles/general/moon_io.arts
pyarts/controlfiles/general/planet_earth.arts
pyarts/controlfiles/general/planet_venus.arts
pyarts/controlfiles/general/agendas.arts
pyarts/controlfiles/general/planet_jupiter.arts
pyarts/controlfiles/instruments/hirs/TestHIRS_reference.arts
pyarts/controlfiles/instruments/hirs/TestHIRS_fast.arts
pyarts/controlfiles/instruments/metmm/common_metmm.arts
pyarts/controlfiles/instruments/metmm/TestMetMM.arts
pyarts/controlfiles/instruments/metmm/sensor_descriptions/sensor_amsua.arts
pyarts/controlfiles/instruments/metmm/sensor_descriptions/sensor_mwhs2.arts
pyarts/controlfiles/instruments/metmm/sensor_descriptions/sensor_ismar_upward.arts
pyarts/controlfiles/instruments/metmm/sensor_descriptions/sensor_hatpro.arts
pyarts/controlfiles/instruments/metmm/sensor_descriptions/sensor_amsub.arts
pyarts/controlfiles/instruments/metmm/sensor_descriptions/sensor_deimos.arts
pyarts/controlfiles/instruments/metmm/sensor_descriptions/sensor_ismar_downward.arts
pyarts/controlfiles/instruments/metmm/sensor_descriptions/prepare_metmm.arts
pyarts-2.4.0.dist-info/WHEEL
pyarts-2.4.0.dist-info/METADATA
pyarts-2.4.0.dist-info/top_level.txt
pyarts-2.4.0.dist-info/RECORD
