Metadata-Version: 2.1
Name: pyarts
Version: 2.4.0
Summary: PyARTS, the Python interface for ARTS
Home-page: https://github.com/atmtools/arts
Author: The Typhon developers
Author-email: arts.mi@lists.uni-hamburg.de
License: MIT
Platform: UNKNOWN
Classifier: Development Status :: 4 - Beta
Classifier: Intended Audience :: Science/Research
Classifier: Topic :: Scientific/Engineering :: Atmospheric Science
Classifier: License :: OSI Approved :: MIT License
Classifier: Programming Language :: Python :: 3.7
Requires-Python: >=3.6
Requires-Dist: docutils
Requires-Dist: matplotlib (>=1.4)
Requires-Dist: netCDF4 (>=1.1.1)
Requires-Dist: numpy (>=1.13)
Requires-Dist: scipy (>=0.15.1)
Requires-Dist: setuptools (>=0.7.2)
Provides-Extra: docs
Requires-Dist: sphinx-rtd-theme ; extra == 'docs'
Provides-Extra: tests
Requires-Dist: pytest ; extra == 'tests'
Requires-Dist: pint ; extra == 'tests'
Requires-Dist: gdal ; extra == 'tests'
